py400/AS400.py
py400/__init__.py
py400-0.6.4.dist-info/METADATA
py400-0.6.4.dist-info/WHEEL
py400-0.6.4.dist-info/top_level.txt
py400-0.6.4.dist-info/RECORD
