Metadata-Version: 2.4
Name: py400
Version: 0.6.4
Summary: A library to facilitate interactions with IBM i hosts using python.
Requires-Dist: itoolkit>=1.7.2
Requires-Dist: pyodbc>=5.1.0
Dynamic: requires-dist
Dynamic: summary
